{
    "data": [
        {
            "code": "CS-352",
            "name": "Compiler Design",
            "groups": [
                {
                    "platform": "whatsapp",
                    "url": "https://chat.whatsapp.com/He5G9M1dcrn5J3q5cLMO9E",
                    "term": "Spring/2022"
                }
            ]
        },
        {
            "code": "phy 101",
            "groups": [
                {
                    "platform": "whatsapp",
                    "url": "https://chat.whatsapp.com/ClzZETpN0CA2QRAzxrHKoQ",
                    "term": "Spring/2022"
                }
            ]
        },
        {
            "code": "CS301 Data comm. & Network",
            "groups": [
                {
                    "platform": "whatsapp",
                    "url": "https://chat.whatsapp.com/LcnE65q0Ur77AK4XOwfDfr",
                    "term": "Spring/2022"
                }
            ]
        },
        {
            "code": "CS-311 Assembly",
            "groups": [
                {
                    "platform": "whatsapp",
                    "url": "https://chat.whatsapp.com/DgD8B49c2F25MYMPRmiYwc",
                    "term": "Spring/2022"
                }
            ]
        },
        {
            "code": "CS312 Modern Dev. Tools",
            "groups": [
                {
                    "platform": "whatsapp",
                    "url": "https://chat.whatsapp.com/BUgyLdlkAf5DH9kjb0DCjS",
                    "term": "Spring/2022"
                }
            ]
        },
        {
            "code": "CS321 Theory of Comp.",
            "groups": [
                {
                    "platform": "whatsapp",
                    "url": "https://chat.whatsapp.com/EJlNBEkZ7Va8BtdEjjFcRS",
                    "term": "Spring/2022"
                }
            ]
        },
        {
            "code": "CS361 Introduction to AI",
            "groups": [
                {
                    "platform": "whatsapp",
                    "url": "https://chat.whatsapp.com/FHNuW5SqewpAbYzoPnDfjz",
                    "term": "Spring/2022"
                }
            ]
        },
        {
            "code": "CS402 Computer Graphics",
            "groups": [
                {
                    "platform": "whatsapp",
                    "url": "https://chat.whatsapp.com/I3MclVrXveU5iIvDcdLPqd",
                    "term": "Spring/2022"
                }
            ]
        },
        {
            "code": "CS481 Pattern Recognition",
            "groups": [
                {
                    "platform": "whatsapp",
                    "url": "https://chat.whatsapp.com/JXY26f8IHGBE8j8jJG5KKU",
                    "term": "Spring/2022"
                }
            ]
        },
        {
            "code": "IS231 Operating Research",
            "groups": [
                {
                    "platform": "whatsapp",
                    "url": "https://chat.whatsapp.com/GFCIxxz7z8pBAKfaTTXTSQ",
                    "term": "Spring/2022"
                }
            ]
        },
        {
            "code": "IS321 Intro. to Database",
            "groups": [
                {
                    "platform": "whatsapp",
                    "url": "https://chat.whatsapp.com/HwnpeYB7Q9a4xjcEcM5LdS",
                    "term": "Spring/2022"
                }
            ]
        },
        {
            "code": "algorithm",
            "groups": [
                {
                    "platform": "whatsapp",
                    "url": "https://chat.whatsapp.com/Ix3Q4ubBFX9BA226PEfiM5",
                    "term": "Spring/2022"
                }
            ]
        },
        {
            "code": "ECE210",
            "groups": [
                {
                    "platform": "whatsapp",
                    "url": "https://chat.whatsapp.com/LqzIrtTsTxK7DPpQUcXZeT",
                    "term": "Spring/2022"
                }
            ]
        },
        {
            "code": "math 301",
            "groups": [
                {
                    "platform": "whatsapp",
                    "url": "https://chat.whatsapp.com/DxaHZnUZJmzFgAZMdPYOS8",
                    "term": "Spring/2022"
                }
            ]
        },
        {
            "code": "CS251",
            "groups": [
                {
                    "platform": "whatsapp",
                    "url": "https://chat.whatsapp.com/KXq0yfoCsPb53sT2xVxBJo",
                    "term": "Spring/2022"
                }
            ]
        },
        {
            "code": "CS483-mulitmedia",
            "groups": [
                {
                    "platform": "whatsapp",
                    "url": "https://chat.whatsapp.com/GgDiOU3cyDqKPopK9tRhEg",
                    "term": "Spring/2022"
                }
            ]
        },
        {
            "code": "CS409-selected topics in cs",
            "groups": [
                {
                    "platform": "whatsapp",
                    "url": "https://chat.whatsapp.com/JcxCbr2oBRj37xMYWOdHpR",
                    "term": "Spring/2022"
                }
            ]
        },
        {
            "code": "eng201",
            "groups": [
                {
                    "platform": "whatsapp",
                    "url": "https://chat.whatsapp.com/CKo9bKZv28G3B9Nwwv1C3I",
                    "term": "Spring/2022"
                }
            ]
        },
        {
            "code": "CS212 data structure",
            "groups": [
                {
                    "platform": "whatsapp",
                    "url": "https://chat.whatsapp.com/FNJnmp6AcfBCvRCJQpIfxf",
                    "term": "Spring/2022"
                }
            ]
        },
        {
            "code": "CS102",
            "groups": [
                {
                    "platform": "whatsapp",
                    "url": "https://chat.whatsapp.com/E8k4bUPeSjR6sONI5Zu2mO",
                    "term": "Spring/2022"
                }
            ]
        },
        {
            "code": "math102",
            "groups": [
                {
                    "platform": "whatsapp",
                    "url": "https://chat.whatsapp.com/FOqRDxdf8qlInV8lx19uvI",
                    "term": "Spring/2022"
                }
            ]
        },
        {
            "code": "math251",
            "groups": [
                {
                    "platform": "whatsapp",
                    "url": "https://chat.whatsapp.com/GQjjbNQ9tKg63vsKCE9PeV",
                    "term": "Spring/2022"
                }
            ]
        },
        {
            "code": "is101",
            "groups": [
                {
                    "platform": "whatsapp",
                    "url": "https://chat.whatsapp.com/KFYa6tmhosi5Dac1u6L696",
                    "term": "Spring/2022"
                }
            ]
        },
        {
            "code": "phy102",
            "groups": [
                {
                    "platform": "whatsapp",
                    "url": "https://chat.whatsapp.com/JXzHWhBhOVr21xqcLE7QiJ",
                    "term": "Spring/2022"
                }
            ]
        },
        {
            "code": "Arab101",
            "groups": [
                {
                    "platform": "whatsapp",
                    "url": "https://chat.whatsapp.com/J3ZhGsbgvx6BekophfihwE",
                    "term": "Spring/2022"
                }
            ]
        },
        {
            "code": "Eng099",
            "groups": [
                {
                    "platform": "whatsapp",
                    "url": "https://chat.whatsapp.com/KYp0SMZA9jH1hTQ6tDyxqZ",
                    "term": "Spring/2022"
                }
            ]
        },
        {
            "code": "Eng101",
            "groups": [
                {
                    "platform": "whatsapp",
                    "url": "https://chat.whatsapp.com/BobkKgDNARV4wXtMyvhtA5",
                    "term": "Spring/2022"
                }
            ]
        },
        {
            "code": "Eng102",
            "groups": [
                {
                    "platform": "whatsapp",
                    "url": "https://chat.whatsapp.com/GH7mPXvNM3M4k0pfeZoPfk",
                    "term": "Spring/2022"
                }
            ]
        },
        {
            "code": "Hum101",
            "groups": [
                {
                    "platform": "whatsapp",
                    "url": "https://chat.whatsapp.com/Bcs4Sgh17AeKKDoYdz2pg9",
                    "term": "Spring/2022"
                }
            ]
        },
        {
            "code": "Hum102",
            "groups": [
                {
                    "platform": "whatsapp",
                    "url": "https://chat.whatsapp.com/HLRYH1zAQHZ9vnQszWj73j",
                    "term": "Spring/2022"
                }
            ]
        },
        {
            "code": "Eng098",
            "groups": [
                {
                    "platform": "whatsapp",
                    "url": "https://chat.whatsapp.com/ImYyE40uASfKmLlIIWPvB6",
                    "term": "Spring/2022"
                }
            ]
        },
        {
            "code": "math101",
            "groups": [
                {
                    "platform": "whatsapp",
                    "url": "https://chat.whatsapp.com/BSwI0p58AfY3Zyl6oiPnkE",
                    "term": "Spring/2022"
                }
            ]
        },
        {
            "code": "cs101",
            "groups": [
                {
                    "platform": "whatsapp",
                    "url": "https://chat.whatsapp.com/Fin6bqyUlnV6XM5gI6q912",
                    "term": "Spring/2022"
                }
            ]
        }
    ]
}